mongo_schema/__init__.py
mongo_schema/cli.py
mongo_schema/config.py
mongo_schema/exceptions.py
mongo_schema/exporter.py
mongo_schema/utils.py
mongo_schema_V2-0.1.5.dist-info/METADATA
mongo_schema_V2-0.1.5.dist-info/WHEEL
mongo_schema_V2-0.1.5.dist-info/entry_points.txt
mongo_schema_V2-0.1.5.dist-info/top_level.txt
mongo_schema_V2-0.1.5.dist-info/RECORD
