Metadata-Version: 2.1
Name: mongo-schema-V2
Version: 0.1.5
Summary: A Python SDK for exporting MongoDB schema metadata
Home-page: https://github.com/karanbhatiakb/mongo-schema-V2/tree/master
Author: Karan Bhatia
Author-email: karanbhatia.kb27@gmail.com
License: UNKNOWN
Platform: UNKNOWN
Classifier: Programming Language :: Python :: 3
Classifier: License :: OSI Approved :: MIT License
Classifier: Operating System :: OS Independent
Requires-Python: >=3.6
Requires-Dist: pymongo
Requires-Dist: bson
